ncache/__init__.py
ncache/client/CQEventArg.py
ncache/client/Cache.py
ncache/client/CacheConnection.py
ncache/client/CacheConnectionOptions.py
ncache/client/CacheEventArg.py
ncache/client/CacheEventDescriptor.py
ncache/client/CacheItem.py
ncache/client/CacheItemAttributes.py
ncache/client/CacheItemVersion.py
ncache/client/CacheManager.py
ncache/client/CacheReader.py
ncache/client/ClientInfo.py
ncache/client/ClusterEvent.py
ncache/client/ContinuousQuery.py
ncache/client/Credentials.py
ncache/client/EventArg.py
ncache/client/EventCacheItem.py
ncache/client/LockHandle.py
ncache/client/QueryCommand.py
ncache/client/ServerInfo.py
ncache/client/__init__.py
ncache/client/datastructures/Counter.py
ncache/client/datastructures/DataStructureAttributes.py
ncache/client/datastructures/DataStructureEventArg.py
ncache/client/datastructures/DataStructureManager.py
ncache/client/datastructures/DistributedDictionary.py
ncache/client/datastructures/DistributedHashSet.py
ncache/client/datastructures/DistributedList.py
ncache/client/datastructures/DistributedQueue.py
ncache/client/datastructures/__init__.py
ncache/client/enum/CacheItemPriority.py
ncache/client/enum/CacheItemRemovedReason.py
ncache/client/enum/CacheStatusNotificationType.py
ncache/client/enum/ClientCacheSyncMode.py
ncache/client/enum/CmdParamsType.py
ncache/client/enum/CommandType.py
ncache/client/enum/ConnectivityStatus.py
ncache/client/enum/DataTypeEventDataFilter.py
ncache/client/enum/DeliveryMode.py
ncache/client/enum/DeliveryOption.py
ncache/client/enum/DistributedDataStructure.py
ncache/client/enum/EntryType.py
ncache/client/enum/EventDataFilter.py
ncache/client/enum/EventType.py
ncache/client/enum/ExpirationType.py
ncache/client/enum/IsolationLevel.py
ncache/client/enum/KeyDependencyType.py
ncache/client/enum/LogLevel.py
ncache/client/enum/MessgeFailureReason.py
ncache/client/enum/OpType.py
ncache/client/enum/OracleCmdParamsType.py
ncache/client/enum/OracleCommandType.py
ay_aussama_client-0.1.dist-info/LICENSE
ay_aussama_client-0.1.dist-info/METADATA
ay_aussama_client-0.1.dist-info/WHEEL
ay_aussama_client-0.1.dist-info/top_level.txt
ay_aussama_client-0.1.dist-info/RECORD
