Metadata-Version: 2.1
Name: ay-aussama-client
Version: 0.1
Summary: Ay-Aussama client for QA Testing.
Home-page: UNKNOWN
Author: AyAussama
Author-email: ay_aussama@email.com
License: UNKNOWN
Platform: UNKNOWN
Classifier: Programming Language :: Python :: 3
Classifier: License :: OSI Approved :: MIT License
Classifier: Operating System :: OS Independent
Requires-Python: >=3.5
License-File: LICENSE
Requires-Dist: jpype1
Requires-Dist: jsons
